pripessoaink/flashday/__init__.py
pripessoaink/flashday/admin.py
pripessoaink/flashday/apps.py
pripessoaink/flashday/models.py
pripessoaink/flashday/tests.py
pripessoaink/flashday/urls.py
pripessoaink/flashday/views.py
pripessoaink/flashday/management/commands/default_option.py
pripessoaink/flashday/management/commands/set_prices.py
pripessoaink/flashday/migrations/__init__.py
pripessoaink/flashday/templates/flashday/home.html
pripessoaink/flashday/templates/flashday/informativo-antiplagio.html
pripessoaink/flashday/templates/flashday/product.html
pripessoaink/flashday/templatetags/__init__.py
pripessoaink/flashday/templatetags/flashday.py
flashday-0.3.0.dist-info/LICENSE
flashday-0.3.0.dist-info/METADATA
flashday-0.3.0.dist-info/WHEEL
flashday-0.3.0.dist-info/entry_points.txt
flashday-0.3.0.dist-info/top_level.txt
flashday-0.3.0.dist-info/RECORD
