Metadata-Version: 2.1
Name: flashday
Version: 0.3.0
Summary: Flashday event Django app
Home-page: https://github.com/pripessoaink/flashday
Author: Arthur Henrique Della Fraga
Author-email: Arthur Henrique Della Fraga <Arthur.Henrique.Della.Fraga@gmail.com>
License: GNU General Public License v3.0
Platform: Linux #54~20.04.1-Ubuntu SMP Sat Mar 20 13:40:25 UTC 2021 x86_64
Classifier: Programming Language :: Python :: Implementation :: CPython
Classifier: Programming Language :: Python :: 3
Classifier: Programming Language :: Python :: 3 :: Only
Classifier: Programming Language :: Python :: 3.8
Classifier: Operating System :: POSIX :: Linux
Classifier: Development Status :: 1 - Planning
Classifier: Intended Audience :: Customer Service
Classifier: Framework :: Django
Classifier: Framework :: Django :: 3.1
Classifier: Topic :: Software Development :: Libraries
Classifier: Topic :: Software Development :: Libraries :: Python Modules
Classifier: Topic :: Utilities
Requires-Python: >=3.8
Requires-Dist: Django (<4.x,>=3.1)
Provides-Extra: dev
Requires-Dist: pip (<22.0,>=21.x) ; extra == 'dev'
Requires-Dist: setuptools (<55.0,>=54.x) ; extra == 'dev'
Requires-Dist: wheel (<1.0,>=0.36) ; extra == 'dev'
Requires-Dist: twine (<4.0,>=3.4) ; extra == 'dev'
Requires-Dist: trove-classifiers (>=2021.x) ; extra == 'dev'
Requires-Dist: GitPython (<4.0,>=3.x) ; extra == 'dev'
Requires-Dist: requests (<3.0,>=2.x) ; extra == 'dev'
